pycountwc/__init__.py
pycountwc/pycountwc.py
pycountwc-1.0.1.dist-info/LICENSE
pycountwc-1.0.1.dist-info/METADATA
pycountwc-1.0.1.dist-info/WHEEL
pycountwc-1.0.1.dist-info/top_level.txt
pycountwc-1.0.1.dist-info/RECORD
